dtwentyecommerce/Error.py
dtwentyecommerce/Payment.py
dtwentyecommerce/Search.py
dtwentyecommerce/Shipping.py
dtwentyecommerce/Shopping.py
dtwentyecommerce/Stock.py
dtwentyecommerce/User.py
dtwentyecommerce/__init__.py
dtwentyecommerce/dev_tools.py
dtwentyecommerce/tools.py
dtwentyecommerce/Classes/Address.py
dtwentyecommerce/Classes/AppliesTo.py
dtwentyecommerce/Classes/Availability.py
dtwentyecommerce/Classes/BelongsTo.py
dtwentyecommerce/Classes/Brand.py
dtwentyecommerce/Classes/Cart.py
dtwentyecommerce/Classes/CartContains.py
dtwentyecommerce/Classes/Category.py
dtwentyecommerce/Classes/Charge.py
dtwentyecommerce/Classes/Checkout.py
dtwentyecommerce/Classes/Converted.py
dtwentyecommerce/Classes/DeliveredBy.py
dtwentyecommerce/Classes/Delivery.py
dtwentyecommerce/Classes/DeliveryRule.py
dtwentyecommerce/Classes/Element.py
dtwentyecommerce/Classes/File.py
dtwentyecommerce/Classes/Holds.py
dtwentyecommerce/Classes/Included.py
dtwentyecommerce/Classes/IncludesPromo.py
dtwentyecommerce/Classes/Invoice.py
dtwentyecommerce/Classes/InvoiceAt.py
dtwentyecommerce/Classes/LocatedAt.py
dtwentyecommerce/Classes/Makes.py
dtwentyecommerce/Classes/OfferedBy.py
dtwentyecommerce/Classes/Order.py
dtwentyecommerce/Classes/OrderContains.py
dtwentyecommerce/Classes/PaidBy.py
dtwentyecommerce/Classes/Payment.py
dtwentyecommerce/Classes/PaymentMethod.py
dtwentyecommerce/Classes/PaysWith.py
dtwentyecommerce/Classes/Price.py
dtwentyecommerce/Classes/Product.py
dtwentyecommerce/Classes/ProductImage.py
dtwentyecommerce/Classes/Promotion.py
dtwentyecommerce/Classes/Purchased.py
dtwentyecommerce/Classes/Query.py
dtwentyecommerce/Classes/ReceivesAt.py
dtwentyecommerce/Classes/Retrieved.py
dtwentyecommerce/Classes/Searched.py
dtwentyecommerce/Classes/Selected.py
dtwentyecommerce/Classes/SellsFor.py
dtwentyecommerce/Classes/SentBy.py
dtwentyecommerce/Classes/SentTo.py
dtwentyecommerce/Classes/Settled.py
dtwentyecommerce/Classes/Stock.py
dtwentyecommerce/Classes/TaxAddress.py
d20_ecommerce-0.0.0a1.dist-info/LICENSE
d20_ecommerce-0.0.0a1.dist-info/METADATA
d20_ecommerce-0.0.0a1.dist-info/WHEEL
d20_ecommerce-0.0.0a1.dist-info/top_level.txt
d20_ecommerce-0.0.0a1.dist-info/RECORD
