Metadata-Version: 2.1
Name: d20-ecommerce
Version: 0.0.0a1
Summary: A simple ecommerce back
Home-page: https://github.com/d20services/ecommerce_python_arango
Author: Alex Sánchez Vega
Author-email: alex@d20.services
Project-URL: Bug Tracker, https://github.com/d20services/ecommerce_python_arango/issues
Classifier: Programming Language :: Python :: 3
Classifier: License :: OSI Approved :: MIT License
Classifier: Operating System :: OS Independent
Requires-Python: >=3.8
License-File: LICENSE
Requires-Dist: pyArango
Requires-Dist: datetime
Requires-Dist: d20-orm
Requires-Dist: cryptography
Requires-Dist: flask
Requires-Dist: d20-communications
Requires-Dist: stripe
